AUTHORS.rst
CHANGELOG.rst
LICENSE.txt
MANIFEST.in
README.rst
setup.cfg
setup.py
nextcloud_news_updater/__init__.py
nextcloud_news_updater/__main__.py
nextcloud_news_updater/config.py
nextcloud_news_updater/container.py
nextcloud_news_updater/version.py
nextcloud_news_updater/version.txt
nextcloud_news_updater.egg-info/PKG-INFO
nextcloud_news_updater.egg-info/SOURCES.txt
nextcloud_news_updater.egg-info/dependency_links.txt
nextcloud_news_updater.egg-info/entry_points.txt
nextcloud_news_updater.egg-info/top_level.txt
nextcloud_news_updater/api/__init__.py
nextcloud_news_updater/api/api.py
nextcloud_news_updater/api/cli.py
nextcloud_news_updater/api/updater.py
nextcloud_news_updater/api/web.py
nextcloud_news_updater/common/__init__.py
nextcloud_news_updater/common/argumentparser.py
nextcloud_news_updater/common/logger.py
nextcloud_news_updater/dependencyinjection/__init__.py
nextcloud_news_updater/dependencyinjection/container.py
tests/__init__.py
tests/nextcloud_news_updater/__init__.py
tests/nextcloud_news_updater/test_config.py
tests/nextcloud_news_updater/api/__init__.py
tests/nextcloud_news_updater/api/test_cli.py
tests/nextcloud_news_updater/api/test_web.py
tests/nextcloud_news_updater/dependencyinjection/__init__.py
tests/nextcloud_news_updater/dependencyinjection/test_container.py
tests/nextcloud_news_updater/updaters/__init__.py