Metadata-Version: 1.1
Name: nextcloud-news-updater
Version: 10.0.1
Summary: Nextcloud News updater - Fast updates for your RSS/Atom feeds
Home-page: https://github.com/nextcloud/news-updater
Author: Bernhard Posselt
Author-email: dev@bernhard-posselt.com
License: GPL
Keywords: nextcloud,news,updater,RSS,Atom,feed,reader
Platform: UNKNOWN
Classifier: Intended Audience :: System Administrators
Classifier: Environment :: Console
Classifier: License :: OSI Approved :: GNU General Public License v3 or later (GPLv3+)
Classifier: Operating System :: POSIX :: Linux
Classifier: Programming Language :: Python :: 3 :: Only
Classifier: Topic :: Utilities
